mortal_var/__init__.py
mortal_var/var_main.cp37-win_amd64.pyd
mortal_var-4.3.0.dist-info/METADATA
mortal_var-4.3.0.dist-info/WHEEL
mortal_var-4.3.0.dist-info/top_level.txt
mortal_var-4.3.0.dist-info/RECORD
