Metadata-Version: 2.1
Name: mortal-var
Version: 4.3.0
Summary: mortal工具集::mortal_var
Home-page: https://www.example.com
Author: Mortal
Author-email: mortal9098@163.com
License: MIT
Classifier: Development Status :: 4 - Beta
Classifier: Programming Language :: Python :: 3
Classifier: Programming Language :: Python :: 3.7
Classifier: Operating System :: Microsoft :: Windows
Classifier: Intended Audience :: Developers
Requires-Python: >=3.7
Requires-Dist: ms9
